README.md
setup.py
kcwebplus/__init__.py
kcwebplus/kcwebplus.py
kcwebplus.egg-info/PKG-INFO
kcwebplus.egg-info/SOURCES.txt
kcwebplus.egg-info/dependency_links.txt
kcwebplus.egg-info/entry_points.txt
kcwebplus.egg-info/requires.txt
kcwebplus.egg-info/top_level.txt
kcwebplus/common/__init__.py
kcwebplus/common/autoload.py
kcwebplus/common/model.py
kcwebplus/config/__init__.py
kcwebplus/config/app.py
kcwebplus/config/database.py
kcwebplus/config/other.py
kcwebplus/config/redis.py
kcwebplus/index/__init__.py
kcwebplus/index/common/__init__.py
kcwebplus/index/common/autoload.py
kcwebplus/index/controller/__init__.py
kcwebplus/index/controller/index/__init__.py
kcwebplus/index/controller/index/admin.py
kcwebplus/index/controller/index/index.py
kcwebplus/index/controller/index/menu.py
kcwebplus/index/controller/index/modular.py
kcwebplus/index/controller/index/mysocket.py
kcwebplus/index/controller/index/plan.py
kcwebplus/index/controller/index/plug.py
kcwebplus/index/controller/index/pub.py
kcwebplus/index/controller/index/setup.py
kcwebplus/index/controller/index/task.py
kcwebplus/index/controller/index/common/__init__.py
kcwebplus/index/controller/index/common/autoload.py
kcwebplus/index/controller/index/common/model.py
kcwebplus/index/controller/index/common/plantask.py
kcwebplus/index/controller/index/tpl/admin/admin.html
kcwebplus/index/controller/index/tpl/admin/adminlog.html
kcwebplus/index/controller/index/tpl/admin/blacklistrole.html
kcwebplus/index/controller/index/tpl/admin/index.html
kcwebplus/index/controller/index/tpl/admin/role.html
kcwebplus/index/controller/index/tpl/index/home.html
kcwebplus/index/controller/index/tpl/index/index.html
kcwebplus/index/controller/index/tpl/menu/index.html
kcwebplus/index/controller/index/tpl/modular/index.html
kcwebplus/index/controller/index/tpl/plan/index.html
kcwebplus/index/controller/index/tpl/plug/index.html
kcwebplus/index/controller/index/tpl/setup/bacrecpage.html
kcwebplus/index/controller/index/tpl/setup/basepage.html
kcwebplus/index/controller/index/tpl/setup/index.html
kcwebplus/index/controller/index/tpl/setup/pythonrun.html
kcwebplus/index/controller/index/tpl/setup/startpage.html
