Metadata-Version: 1.2
Name: kcwebplus
Version: 3.1.88
Summary: kcwebplus是建立在 kcweb 框架的基础上研发的一套 linux 服务器容器系统
Home-page: https://docs.kwebapp.cn/index/index/3
Author: 百里-坤坤
Author-email: kcweb@kwebapp.cn
Maintainer: 百里
Maintainer-email: fk1402936534@qq.com
License: Apache License 2.0
Keywords: kcwebplus3.1.88
Platform: UNKNOWN
